{
	"configurations" : 
	[
		{
			"directories" : 
			[
				{
					"build" : ".",
					"jsonFile" : "directory-.-Debug-d0094a50bb2071803777.json",
					"minimumCMakeVersion" : 
					{
						"string" : "3.21"
					},
					"projectIndex" : 0,
					"source" : ".",
					"targetIndexes" : 
					[
						0
					]
				}
			],
			"name" : "Debug",
			"projects" : 
			[
				{
					"directoryIndexes" : 
					[
						0
					],
					"name" : "equilateral_triangle",
					"targetIndexes" : 
					[
						0
					]
				}
			],
			"targets" : 
			[
				{
					"directoryIndex" : 0,
					"id" : "equilateral_triangle::@6890427a1f51a3e7e1df",
					"jsonFile" : "target-equilateral_triangle-Debug-8809bd279d6ab905b743.json",
					"name" : "equilateral_triangle",
					"projectIndex" : 0
				}
			]
		}
	],
	"kind" : "codemodel",
	"paths" : 
	{
		"build" : "D:/2_Projects/Contests/equilateral-triangle/cmake-build-debug",
		"source" : "D:/2_Projects/Contests/equilateral-triangle"
	},
	"version" : 
	{
		"major" : 2,
		"minor" : 3
	}
}
